aioeosabi/__init__.py
aioeosabi/account.py
aioeosabi/contracts/__init__.py
aioeosabi/contracts/eosio.py
aioeosabi/contracts/eosio_token.py
aioeosabi/exceptions.py
aioeosabi/keys.py
aioeosabi/rpc.py
aioeosabi/serializer.py
aioeosabi/types/__init__.py
aioeosabi/types/abi.py
aioeosabi/types/authority.py
aioeosabi/types/transaction.py
aioeosabi-0.1.2.dist-info/LICENSE
aioeosabi-0.1.2.dist-info/METADATA
aioeosabi-0.1.2.dist-info/WHEEL
aioeosabi-0.1.2.dist-info/RECORD
