Metadata-Version: 2.1
Name: aioeosabi
Version: 0.1.2
Summary: Async library for interacting with EOS.io blockchain
Home-page: https://github.com/MajicGit/aioeos
License: MIT
Keywords: blockchain,eos,async,eosio,cryptocurrency
Author: MajicGit
Requires-Python: >=3.8,<4.0
Classifier: License :: OSI Approved :: MIT License
Classifier: Programming Language :: Python :: 3
Classifier: Programming Language :: Python :: 3.8
Classifier: Programming Language :: Python :: 3.9
Classifier: Programming Language :: Python :: 3.10
Classifier: Programming Language :: Python :: 3.11
Classifier: Programming Language :: Python :: 3.12
Requires-Dist: aiohttp (>=3.3.1,<4.0.0)
Requires-Dist: antelopy (>=0.2.0,<0.3.0)
Requires-Dist: base58 (==2.0.0)
Requires-Dist: ecdsa (>=0.15,<0.16)
Requires-Dist: pycryptodome (>=3.20.0,<4.0.0)
Project-URL: Documentation, https://aioeos.readthedocs.io/en/latest/
Project-URL: Repository, https://github.com/MajicGit/aioeos
